lazy_loading/__init__.py
lazy_loading/lazy_module.py
lazy_loading/py.typed
lazy_loading-0.2.0.dist-info/licenses/LICENSE.txt
lazy_loading-0.2.0.dist-info/WHEEL
lazy_loading-0.2.0.dist-info/METADATA
lazy_loading-0.2.0.dist-info/RECORD
