Metadata-Version: 2.4
Name: lazy-loading
Version: 0.2.0
Summary: A simple lazy module loader for python
Keywords: lazy,loading,module
Author: yesseruser
Author-email: yesseruser <yesseruseryt@gmail.com>
License-Expression: LGPL-3.0-or-later
License-File: LICENSE.txt
Classifier: Development Status :: 4 - Beta
Classifier: Intended Audience :: Developers
Classifier: Topic :: Software Development :: Libraries :: Python Modules
Classifier: Programming Language :: Python :: 3
Requires-Python: >=3.10
Project-URL: Homepage, https://github.com/yesser-studios/lazy-loading
Project-URL: Issues, https://github.com/yesser-studios/lazy-loading/issues
Project-URL: Repository, https://github.com/yesser-studios/lazy-loading.git
